11:39:09 AM PIT >> WARNING : Error during mutation test
org.pitest.util.PitError: foo

Please copy and paste the information and the complete stacktrace below when reporting an issue
VM : Java HotSpot(TM) 64-Bit Server VM
Vendor : Oracle Corporation
Version : 25.202-b08
Uptime : 11571
Input -> 
BootClassPathSupported : true

	at org.pitest.mutationtest.execute.MutationTestWorker.processMutation(MutationTestWorker.java:91)
	at org.pitest.mutationtest.execute.MutationTestWorker.run(MutationTestWorker.java:77)
	at org.pitest.mutationtest.execute.MutationTestMinion.run(MutationTestMinion.java:88)
	at org.pitest.mutationtest.execute.MutationTestMinionTest.shouldReportErrorWhenOneOccursDuringAnalysis(MutationTestMinionTest.java:83)
	at sun.reflect.NativeMethodAccessorImpl.invoke0(Native Method)
	at sun.reflect.NativeMethodAccessorImpl.invoke(NativeMethodAccessorImpl.java:62)
	at sun.reflect.DelegatingMethodAccessorImpl.invoke(DelegatingMethodAccessorImpl.java:43)
	at java.lang.reflect.Method.invoke(Method.java:498)
	at org.junit.runners.model.FrameworkMethod$1.runReflectiveCall(FrameworkMethod.java:47)
	at org.junit.internal.runners.model.ReflectiveCallable.run(ReflectiveCallable.java:12)
	at org.junit.runners.model.FrameworkMethod.invokeExplosively(FrameworkMethod.java:44)
	at org.junit.internal.runners.statements.InvokeMethod.evaluate(InvokeMethod.java:17)
	at org.junit.internal.runners.statements.RunBefores.evaluate(RunBefores.java:26)
	at org.junit.runners.ParentRunner.runLeaf(ParentRunner.java:271)
	at org.junit.runners.BlockJUnit4ClassRunner.runChild(BlockJUnit4ClassRunner.java:70)
	at org.junit.runners.BlockJUnit4ClassRunner.runChild(BlockJUnit4ClassRunner.java:50)
	at org.junit.runners.ParentRunner$3.run(ParentRunner.java:238)
	at org.junit.runners.ParentRunner$1.schedule(ParentRunner.java:63)
	at org.junit.runners.ParentRunner.runChildren(ParentRunner.java:236)
	at org.junit.runners.ParentRunner.access$000(ParentRunner.java:53)
	at org.junit.runners.ParentRunner$2.evaluate(ParentRunner.java:229)
	at org.junit.runners.ParentRunner.run(ParentRunner.java:309)
	at org.junit.runners.Suite.runChild(Suite.java:127)
	at org.junit.runners.Suite.runChild(Suite.java:26)
	at org.junit.runners.ParentRunner$3.run(ParentRunner.java:238)
	at org.junit.runners.ParentRunner$1.schedule(ParentRunner.java:63)
	at org.junit.runners.ParentRunner.runChildren(ParentRunner.java:236)
	at org.junit.runners.ParentRunner.access$000(ParentRunner.java:53)
	at org.junit.runners.ParentRunner$2.evaluate(ParentRunner.java:229)
	at org.junit.runners.ParentRunner.run(ParentRunner.java:309)
	at org.junit.runner.JUnitCore.run(JUnitCore.java:160)
	at org.junit.runner.JUnitCore.run(JUnitCore.java:138)
	at org.apache.maven.surefire.junitcore.JUnitCoreWrapper.createRequestAndRun(JUnitCoreWrapper.java:113)
	at org.apache.maven.surefire.junitcore.JUnitCoreWrapper.executeEager(JUnitCoreWrapper.java:85)
	at org.apache.maven.surefire.junitcore.JUnitCoreWrapper.execute(JUnitCoreWrapper.java:54)
	at org.apache.maven.surefire.junitcore.JUnitCoreProvider.invoke(JUnitCoreProvider.java:134)
	at org.apache.maven.surefire.booter.ForkedBooter.invokeProviderInSameClassLoader(ForkedBooter.java:200)
	at org.apache.maven.surefire.booter.ForkedBooter.runSuitesInProcess(ForkedBooter.java:153)
	at org.apache.maven.surefire.booter.ForkedBooter.main(ForkedBooter.java:103)
11:39:10 AM PIT >> WARNING : Mutation MutationDetails [id=MutationIdentifier [location=Location [clazz=foo, method=method, methodDesc=()I], indexes=[1], mutator=mutator], filename=sourceFile, block=0, lineNumber=42, description=desc, testsInOrder=[], isInFinallyBlock=false, poison=NORMAL] was not viable 
11:39:10 AM PIT >> INFO : No test coverage for mutation  MutationDetails [id=MutationIdentifier [location=Location [clazz=foo, method=method, methodDesc=()I], indexes=[1], mutator=mutator], filename=sourceFile, block=0, lineNumber=42, description=desc, testsInOrder=[], isInFinallyBlock=false, poison=NORMAL] in method
11:39:10 AM PIT >> INFO : No test coverage for mutation  MutationDetails [id=MutationIdentifier [location=Location [clazz=foo, method=method, methodDesc=()I], indexes=[2], mutator=mutator], filename=sourceFile, block=0, lineNumber=42, description=desc, testsInOrder=[], isInFinallyBlock=false, poison=NORMAL] in method
11:39:12 AM PIT >> WARNING : Could not load org.unknown.Unknown (ClassNotFoundException: org.unknown.Unknown)
java.lang.InterruptedException: sleep interrupted
	at java.lang.Thread.sleep(Native Method)
	at org.pitest.TestJUnitConfiguration$TestWithTimeout.testBar(TestJUnitConfiguration.java:263)
	at sun.reflect.NativeMethodAccessorImpl.invoke0(Native Method)
	at sun.reflect.NativeMethodAccessorImpl.invoke(NativeMethodAccessorImpl.java:62)
	at sun.reflect.DelegatingMethodAccessorImpl.invoke(DelegatingMethodAccessorImpl.java:43)
	at java.lang.reflect.Method.invoke(Method.java:498)
	at org.junit.runners.model.FrameworkMethod$1.runReflectiveCall(FrameworkMethod.java:47)
	at org.junit.internal.runners.model.ReflectiveCallable.run(ReflectiveCallable.java:12)
	at org.junit.runners.model.FrameworkMethod.invokeExplosively(FrameworkMethod.java:44)
	at org.junit.internal.runners.statements.InvokeMethod.evaluate(InvokeMethod.java:17)
	at org.junit.internal.runners.statements.FailOnTimeout$StatementThread.run(FailOnTimeout.java:74)
11:39:17 AM PIT >> WARNING : Found more than one mutation similar on same line in a finally block. Can't correct for inlining.
11:39:17 AM PIT >> WARNING : Using untargetted tests
11:39:17 AM PIT >> WARNING : Found more than one mutation similar on same line in a finally block. Can't correct for inlining.
11:39:17 AM PIT >> WARNING : Found more than one mutation similar on same line in a finally block. Can't correct for inlining.
11:39:17 AM PIT >> WARNING : Found more than one mutation similar on same line in a finally block. Can't correct for inlining.
11:39:17 AM PIT >> WARNING : Found more than one mutation similar on same line in a finally block. Can't correct for inlining.
11:39:17 AM PIT >> WARNING : Found more than one mutation similar on same line in a finally block. Can't correct for inlining.
11:39:17 AM PIT >> WARNING : Found more than one mutation similar on same line in a finally block. Can't correct for inlining.
11:39:17 AM PIT >> WARNING : Found more than one mutation similar on same line in a finally block. Can't correct for inlining.
11:39:17 AM PIT >> WARNING : Found more than one mutation similar on same line in a finally block. Can't correct for inlining.
11:39:17 AM PIT >> WARNING : Found more than one mutation similar on same line in a finally block. Can't correct for inlining.
11:39:17 AM PIT >> WARNING : Found more than one mutation similar on same line in a finally block. Can't correct for inlining.
11:39:17 AM PIT >> WARNING : Found more than one mutation similar on same line in a finally block. Can't correct for inlining.
11:39:17 AM PIT >> WARNING : Found more than one mutation similar on same line in a finally block. Can't correct for inlining.
11:39:17 AM PIT >> WARNING : Found more than one mutation similar on same line in a finally block. Can't correct for inlining.
11:39:17 AM PIT >> WARNING : Found more than one mutation similar on same line in a finally block. Can't correct for inlining.
11:39:18 AM PIT >> WARNING : Could not read previous results
11:39:19 AM PIT >> INFO : Verbose logging is disabled. If you encounter an problem please enable it before reporting an issue.
11:39:19 AM PIT >> INFO : Created  0 mutation test units
11:39:19 AM PIT >> WARNING : No mutations found. This probably means there is an issue with either the supplied classpath or filters.
See http://pitest.org for more details.
11:39:19 AM PIT >> INFO : Completed in 0 seconds
11:39:19 AM PIT >> INFO : Verbose logging is disabled. If you encounter an problem please enable it before reporting an issue.
11:39:19 AM PIT >> INFO : Created  0 mutation test units
11:39:19 AM PIT >> WARNING : No mutations found. This probably means there is an issue with either the supplied classpath or filters.
See http://pitest.org for more details.
11:39:19 AM PIT >> INFO : Completed in 0 seconds
11:39:19 AM PIT >> INFO : Verbose logging is disabled. If you encounter an problem please enable it before reporting an issue.
11:39:19 AM PIT >> INFO : Created  0 mutation test units
11:39:19 AM PIT >> INFO : Verbose logging is disabled. If you encounter an problem please enable it before reporting an issue.
11:39:19 AM PIT >> INFO : Created  0 mutation test units
11:39:19 AM PIT >> WARNING : No mutations found. This probably means there is an issue with either the supplied classpath or filters.
See http://pitest.org for more details.
11:39:19 AM PIT >> INFO : Completed in 0 seconds
11:39:19 AM PIT >> INFO : Verbose logging is disabled. If you encounter an problem please enable it before reporting an issue.
11:39:19 AM PIT >> INFO : Created  0 mutation test units
11:39:19 AM PIT >> WARNING : No mutations found. This probably means there is an issue with either the supplied classpath or filters.
See http://pitest.org for more details.
11:39:19 AM PIT >> INFO : Completed in 0 seconds
11:39:19 AM PIT >> INFO : Sending 2 test classes to minion
11:39:19 AM PIT >> INFO : Sent tests to minion
11:39:19 AM PIT >> INFO : Sending 0 test classes to minion
11:39:19 AM PIT >> INFO : Sent tests to minion
11:39:19 AM PIT >> SEVERE : Description [testClass=null, name=fooTest] did not pass without mutation.
onalsMutatorTest
package asm.org.pitest.mutationtest.engine.gregor.mutators;
import java.util.*;
import org.objectweb.asm.*;
public class NegateConditionalsMutatorTest$HasIF_ACMPNEDump implements Opcodes {

public static byte[] dump () throws Exception {

ClassWriter cw = new ClassWriter(0);
FieldVisitor fv;
MethodVisitor mv;
AnnotationVisitor av0;

cw.visit(V1_6, ACC_SUPER, "org/pitest/mutationtest/engine/gregor/mutators/NegateConditionalsMutatorTest$HasIF_ACMPNE", "Ljava/lang/Object;Ljava/util/concurrent/Callable<Ljava/lang/String;>;", "java/lang/Object", new String[] { "java/util/concurrent/Callable" });

cw.visitSource("NegateConditionalsMutatorTest.java", null);

cw.visitInnerClass("org/pitest/mutationtest/engine/gregor/mutators/NegateConditionalsMutatorTest$HasIF_ACMPNE", "org/pitest/mutationtest/engine/gregor/mutators/NegateConditionalsMutatorTest", "HasIF_ACMPNE", ACC_PRIVATE + ACC_STATIC);

{
fv = cw.visitField(ACC_PRIVATE + ACC_FINAL, "i", "Ljava/lang/Object;", null, null);
fv.visitEnd();
}
{
mv = cw.visitMethod(0, "<init>", "(Ljava/lang/Object;)V", null, null);
mv.visitCode();
Label l0 = new Label();
mv.visitLabel(l0);
mv.visitLineNumber(388, l0);
mv.visitVarInsn(ALOAD, 0);
mv.visitMethodInsn(INVOKESPECIAL, "java/lang/Object", "<init>", "()V", false);
Label l1 = new Label();
mv.visitLabel(l1);
mv.visitLineNumber(389, l1);
mv.visitVarInsn(ALOAD, 0);
mv.visitVarInsn(ALOAD, 1);
mv.visitFieldInsn(PUTFIELD, "org/pitest/mutationtest/engine/gregor/mutators/NegateConditionalsMutatorTest$HasIF_ACMPNE", "i", "Ljava/lang/Object;");
Label l2 = new Label();
mv.visitLabel(l2);
mv.visitLineNumber(390, l2);
mv.visitInsn(RETURN);
Label l3 = new Label();
mv.visitLabel(l3);
mv.visitLocalVariable("this", "Lorg/pitest/mutationtest/engine/gregor/mutators/NegateConditionalsMutatorTest$HasIF_ACMPNE;", null, l0, l3, 0);
mv.visitLocalVariable("i", "Ljava/lang/Object;", null, l0, l3, 1);
mv.visitMaxs(2, 2);
mv.visitEnd();
}
{
mv = cw.visitMethod(ACC_PUBLIC, "call", "()Ljava/lang/String;", null, null);
mv.visitCode();
Label l0 = new Label();
mv.visitLabel(l0);
mv.visitLineNumber(394, l0);
mv.visitLdcInsn(Type.getType("Ljava/lang/Integer;"));
mv.visitVarInsn(ASTORE, 1);
Label l1 = new Label();
mv.visitLabel(l1);
mv.visitLineNumber(395, l1);
mv.visitVarInsn(ALOAD, 0);
mv.visitFieldInsn(GETFIELD, "org/pitest/mutationtest/engine/gregor/mutators/NegateConditionalsMutatorTest$HasIF_ACMPNE", "i", "Ljava/lang/Object;");
mv.visitVarInsn(ALOAD, 1);
Label l2 = new Label();
mv.visitJumpInsn(IF_ACMPEQ, l2);
Label l3 = new Label();
mv.visitLabel(l3);
mv.visitLineNumber(396, l3);
mv.visitLdcInsn("was integer");
mv.visitInsn(ARETURN);
mv.visitLabel(l2);
mv.visitLineNumber(398, l2);
mv.visitFrame(Opcodes.F_NEW, 2, new Object[] {"org/pitest/mutationtest/engine/gregor/mutators/NegateConditionalsMutatorTest$HasIF_ACMPNE", "java/lang/Object"}, 0, new Object[] {});
mv.visitLdcInsn("was not integer");
mv.visitInsn(ARETURN);
Label l4 = new Label();
mv.visitLabel(l4);
mv.visitLocalVariable("this", "Lorg/pitest/mutationtest/engine/gregor/mutators/NegateConditionalsMutatorTest$HasIF_ACMPNE;", null, l0, l4, 0);
mv.visitLocalVariable("integer", "Ljava/lang/Object;", null, l1, l4, 1);
mv.visitMaxs(2, 2);
mv.visitEnd();
}
{
mv = cw.visitMethod(ACC_PUBLIC + ACC_BRIDGE + ACC_SYNTHETIC, "call", "()Ljava/lang/Object;", null, new String[] { "java/lang/Exception" });
mv.visitCode();
Label l0 = new Label();
mv.visitLabel(l0);
mv.visitLineNumber(385, l0);
mv.visitVarInsn(ALOAD, 0);
mv.visitMethodInsn(INVOKEVIRTUAL, "org/pitest/mutationtest/engine/gregor/mutators/NegateConditionalsMutatorTest$HasIF_ACMPNE", "call", "()Ljava/lang/String;", false);
mv.visitInsn(ARETURN);
Label l1 = new Label();
mv.visitLabel(l1);
mv.visitLocalVariable("this", "Lorg/pitest/mutationtest/engine/gregor/mutators/NegateConditionalsMutatorTest$HasIF_ACMPNE;", null, l0, l1, 0);
mv.visitMaxs(1, 1);
mv.visitEnd();
}
cw.visitEnd();

return cw.toByteArray();
}
}
Tests run: 16, Failures: 0, Errors: 0, Skipped: 0, Time elapsed: 1.03 sec - in org.pitest.mutationtest.engine.gregor.mutators.NegateConditionalsMutatorTest
Running org.pitest.mutationtest.engine.gregor.MethodInfoTest
Tests run: 18, Failures: 0, Errors: 0, Skipped: 0, Time elapsed: 0.014 sec - in org.pitest.mutationtest.engine.gregor.MethodInfoTest
Running org.pitest.mutationtest.engine.gregor.AvoidAssertsMethodAdapterTest
Tests run: 31, Failures: 0, Errors: 0, Skipped: 0, Time elapsed: 0.06 sec - in org.pitest.mutationtest.engine.gregor.AvoidAssertsMethodAdapterTest
Running org.pitest.mutationtest.engine.gregor.analysis.InstructionTrackingMethodVisitorTest
Tests run: 3, Failures: 0, Errors: 0, Skipped: 0, Time elapsed: 0.022 sec - in org.pitest.mutationtest.engine.gregor.analysis.InstructionTrackingMethodVisitorTest
Running org.pitest.mutationtest.engine.gregor.AvoidStringSwitchedMethodAdapterTest
Tests run: 30, Failures: 0, Errors: 0, Skipped: 0, Time elapsed: 0.036 sec - in org.pitest.mutationtest.engine.gregor.AvoidStringSwitchedMethodAdapterTest
Running org.pitest.mutationtest.engine.gregor.TestGregorMutater
Tests run: 19, Failures: 0, Errors: 0, Skipped: 0, Time elapsed: 0.234 sec - in org.pitest.mutationtest.engine.gregor.TestGregorMutater
Running org.pitest.mutationtest.engine.gregor.GregorMutationEngineTest
Tests run: 1, Failures: 0, Errors: 0, Skipped: 0, Time elapsed: 0.006 sec - in org.pitest.mutationtest.engine.gregor.GregorMutationEngineTest
Running org.pitest.mutationtest.engine.MutationDetailsTest
Tests run: 3, Failures: 0, Errors: 0, Skipped: 0, Time elapsed: 0.322 sec - in org.pitest.mutationtest.engine.MutationDetailsTest
Running org.pitest.mutationtest.engine.LocationTest
Tests run: 2, Failures: 0, Errors: 0, Skipped: 0, Time elapsed: 0.069 sec - in org.pitest.mutationtest.engine.LocationTest
Running org.pitest.mutationtest.engine.MutationIdentifierTest
Tests run: 13, Failures: 0, Errors: 0, Skipped: 0, Time elapsed: 0.069 sec - in org.pitest.mutationtest.engine.MutationIdentifierTest
Running org.pitest.mutationtest.execute.MutationTestMinionTest
org.pitest.util.PitError: foo

Please copy and paste the information and the complete stacktrace below when reporting an issue
VM : Java HotSpot(TM) 64-Bit Server VM
Vendor : Oracle Corporation
Version : 25.202-b08
Uptime : 11571
Input -> 
BootClassPathSupported : true

	at org.pitest.mutationtest.execute.MutationTestWorker.processMutation(MutationTestWorker.java:91)
	at org.pitest.mutationtest.execute.MutationTestWorker.run(MutationTestWorker.java:77)
	at org.pitest.mutationtest.execute.MutationTestMinion.run(MutationTestMinion.java:88)
	at org.pitest.mutationtest.execute.MutationTestMinionTest.shouldReportErrorWhenOneOccursDuringAnalysis(MutationTestMinionTest.java:83)
	at sun.reflect.NativeMethodAccessorImpl.invoke0(Native Method)
	at sun.reflect.NativeMethodAccessorImpl.invoke(NativeMethodAccessorImpl.java:62)
	at sun.reflect.DelegatingMethodAccessorImpl.invoke(DelegatingMethodAccessorImpl.java:43)
	at java.lang.reflect.Method.invoke(Method.java:498)
	at org.junit.runners.model.FrameworkMethod$1.runReflectiveCall(FrameworkMethod.java:47)
	at org.junit.internal.runners.model.ReflectiveCallable.run(ReflectiveCallable.java:12)
	at org.junit.runners.model.FrameworkMethod.invokeExplosively(FrameworkMethod.java:44)
	at org.junit.internal.runners.statements.InvokeMethod.evaluate(InvokeMethod.java:17)
	at org.junit.internal.runners.statements.RunBefores.evaluate(RunBefores.java:26)
	at org.junit.runners.ParentRunner.runLeaf(ParentRunner.java:271)
	at org.junit.runners.BlockJUnit4ClassRunner.runChild(BlockJUnit4ClassRunner.java:70)
	at org.junit.runners.BlockJUnit4ClassRunner.runChild(BlockJUnit4ClassRunner.java:50)
	at org.junit.runners.ParentRunner$3.run(ParentRunner.java:238)
	at org.junit.runners.ParentRunner$1.schedule(ParentRunner.java:63)
	at org.junit.runners.ParentRunner.runChildren(ParentRunner.java:236)
	at org.junit.runners.ParentRunner.access$000(ParentRunner.java:53)
	at org.junit.runners.ParentRunner$2.evaluate(ParentRunner.java:229)
	at org.junit.runners.ParentRunner.run(ParentRunner.java:309)
	at org.junit.runners.Suite.runChild(Suite.java:127)
	at org.junit.runners.Suite.runChild(Suite.java:26)
	at org.junit.runners.ParentRunner$3.run(ParentRunner.java:238)
	at org.junit.runners.ParentRunner$1.schedule(ParentRunner.java:63)
	at org.junit.runners.ParentRunner.runChildren(ParentRunner.java:236)
	at org.junit.runners.ParentRunner.access$000(ParentRunner.java:53)
	at org.junit.runners.ParentRunner$2.evaluate(ParentRunner.java:229)
	at org.junit.runners.ParentRunner.run(ParentRunner.java:309)
	at org.junit.runner.JUnitCore.run(JUnitCore.java:160)
	at org.junit.runner.JUnitCore.run(JUnitCore.java:138)
	at org.apache.maven.surefire.junitcore.JUnitCoreWrapper.createRequestAndRun(JUnitCoreWrapper.java:113)
	at org.apache.maven.surefire.junitcore.JUnitCoreWrapper.executeEager(JUnitCoreWrapper.java:85)
	at org.apache.maven.surefire.junitcore.JUnitCoreWrapper.execute(JUnitCoreWrapper.java:54)
	at org.apache.maven.surefire.junitcore.JUnitCoreProvider.invoke(JUnitCoreProvider.java:134)
	at org.apache.maven.surefire.booter.ForkedBooter.invokeProviderInSameClassLoader(ForkedBooter.java:200)
	at org.apache.maven.surefire.booter.ForkedBooter.runSuitesInProcess(ForkedBooter.java:153)
	at org.apache.maven.surefire.booter.ForkedBooter.main(ForkedBooter.java:103)
Tests run: 2, Failures: 0, Errors: 0, Skipped: 0, Time elapsed: 0.055 sec - in org.pitest.mutationtest.execute.MutationTestMinionTest
Running org.pitest.mutationtest.execute.TimeOutDecoratedTestSourceTest
Tests run: 3, Failures: 0, Errors: 0, Skipped: 0, Time elapsed: 0.009 sec - in org.pitest.mutationtest.execute.TimeOutDecoratedTestSourceTest
Running org.pitest.mutationtest.execute.CheckTestHasFailedResultListenerTest
Tests run: 4, Failures: 0, Errors: 0, Skipped: 0, Time elapsed: 0.001 sec - in org.pitest.mutationtest.execute.CheckTestHasFailedResultListenerTest
Running org.pitest.mutationtest.execute.MutationTimeoutDecoratorTest
Tests run: 2, Failures: 0, Errors: 0, Skipped: 0, Time elapsed: 0.07 sec - in org.pitest.mutationtest.execute.MutationTimeoutDecoratorTest
Running org.pitest.mutationtest.execute.MutationTestWorkerTest
Tests run: 5, Failures: 0, Errors: 0, Skipped: 1, Time elapsed: 0.039 sec - in org.pitest.mutationtest.execute.MutationTestWorkerTest
Running org.pitest.mutationtest.execute.TimeOutSystemExitSideEffectTest
Tests run: 1, Failures: 0, Errors: 0, Skipped: 0, Time elapsed: 0.005 sec - in org.pitest.mutationtest.execute.TimeOutSystemExitSideEffectTest
Running org.pitest.mutationtest.execute.DefaultReporterTest
Tests run: 3, Failures: 0, Errors: 0, Skipped: 0, Time elapsed: 0.008 sec - in org.pitest.mutationtest.execute.DefaultReporterTest
Running org.pitest.mutationtest.MutationStatusTestPairTest
Tests run: 1, Failures: 0, Errors: 0, Skipped: 0, Time elapsed: 0.133 sec - in org.pitest.mutationtest.MutationStatusTestPairTest
Running org.pitest.mutationtest.DetectionStatusTest
Tests run: 12, Failures: 0, Errors: 0, Skipped: 0, Time elapsed: 0.008 sec - in org.pitest.mutationtest.DetectionStatusTest
Running org.pitest.mutationtest.mocksupport.JavassistInputStreamInterceptorAdapaterTest
Tests run: 4, Failures: 0, Errors: 0, Skipped: 0, Time elapsed: 0.01 sec - in org.pitest.mutationtest.mocksupport.JavassistInputStreamInterceptorAdapaterTest
Running org.pitest.mutationtest.mocksupport.BendJavassistToMyWillTransformerTest
Tests run: 2, Failures: 0, Errors: 0, Skipped: 0, Time elapsed: 0.988 sec - in org.pitest.mutationtest.mocksupport.BendJavassistToMyWillTransformerTest
Running org.pitest.mutationtest.mocksupport.JavassistInterceptorTest
Tests run: 3, Failures: 0, Errors: 0, Skipped: 0, Time elapsed: 0.014 sec - in org.pitest.mutationtest.mocksupport.JavassistInterceptorTest
Running org.pitest.mutationtest.build.PercentAndConstantTimeoutStrategyTest
Tests run: 1, Failures: 0, Errors: 0, Skipped: 0, Time elapsed: 0.006 sec - in org.pitest.mutationtest.build.PercentAndConstantTimeoutStrategyTest
Running org.pitest.containers.TestContainersSendCorrectNotifications
Tests run: 2, Failures: 0, Errors: 0, Skipped: 0, Time elapsed: 0.018 sec - in org.pitest.containers.TestContainersSendCorrectNotifications
Running org.pitest.simpletest.steps.NoArgsInstantiateStepTest
Tests run: 2, Failures: 0, Errors: 0, Skipped: 0, Time elapsed: 0.003 sec - in org.pitest.simpletest.steps.NoArgsInstantiateStepTest
Running org.pitest.simpletest.steps.CallStepTest
Tests run: 1, Failures: 0, Errors: 0, Skipped: 0, Time elapsed: 0.001 sec - in org.pitest.simpletest.steps.CallStepTest
Running org.pitest.simpletest.EqualitySetTest
Tests run: 8, Failures: 0, Errors: 0, Skipped: 0, Time elapsed: 0.005 sec - in org.pitest.simpletest.EqualitySetTest
Running org.pitest.simpletest.TestMethodTest
Tests run: 1, Failures: 0, Errors: 0, Skipped: 0, Time elapsed: 0.001 sec - in org.pitest.simpletest.TestMethodTest
Running org.pitest.simpletest.NoArgsConstructorInstantiationStrategyTest
Tests run: 2, Failures: 0, Errors: 0, Skipped: 0, Time elapsed: 0 sec - in org.pitest.simpletest.NoArgsConstructorInstantiationStrategyTest
Running org.pitest.simpletest.SignatureEqualityStrategyTest
Tests run: 3, Failures: 0, Errors: 0, Skipped: 0, Time elapsed: 0.002 sec - in org.pitest.simpletest.SignatureEqualityStrategyTest
Running org.pitest.bytecode.FrameOptionsTest
Tests run: 8, Failures: 0, Errors: 0, Skipped: 0, Time elapsed: 0.001 sec - in org.pitest.bytecode.FrameOptionsTest
Running org.pitest.junit.RunnerSuiteFinderTest
Tests run: 6, Failures: 0, Errors: 0, Skipped: 0, Time elapsed: 0.037 sec - in org.pitest.junit.RunnerSuiteFinderTest
Running org.pitest.junit.JUnitCustomRunnerTestUnitFinderTest
Tests run: 15, Failures: 0, Errors: 0, Skipped: 0, Time elapsed: 0.076 sec - in org.pitest.junit.JUnitCustomRunnerTestUnitFinderTest
Running org.pitest.junit.JUnitCompatibleConfigurationTest
Tests run: 4, Failures: 0, Errors: 0, Skipped: 0, Time elapsed: 0 sec - in org.pitest.junit.JUnitCompatibleConfigurationTest
Running org.pitest.junit.adapter.CustomRunnerExecutorTest
Tests run: 1, Failures: 0, Errors: 0, Skipped: 0, Time elapsed: 0.013 sec - in org.pitest.junit.adapter.CustomRunnerExecutorTest
Running org.pitest.junit.adapter.AdaptingRunListenerTest
Tests run: 6, Failures: 0, Errors: 0, Skipped: 0, Time elapsed: 0.015 sec - in org.pitest.junit.adapter.AdaptingRunListenerTest
Running org.pitest.junit.adapter.AdaptedJUnitTestUnitTest
Tests run: 6, Failures: 0, Errors: 0, Skipped: 0, Time elapsed: 0.038 sec - in org.pitest.junit.adapter.AdaptedJUnitTestUnitTest
Running org.pitest.junit.adapter.ForeignClassLoaderAdaptingRunListenerTest
Tests run: 6, Failures: 0, Errors: 0, Skipped: 0, Time elapsed: 0.054 sec - in org.pitest.junit.adapter.ForeignClassLoaderAdaptingRunListenerTest
Running org.pitest.junit.JUnit4SuiteFinderTest
Tests run: 2, Failures: 0, Errors: 0, Skipped: 0, Time elapsed: 0.001 sec - in org.pitest.junit.JUnit4SuiteFinderTest
Running org.pitest.junit.JUnitTestClassIdentifierTest
Tests run: 15, Failures: 0, Errors: 0, Skipped: 2, Time elapsed: 0.045 sec - in org.pitest.junit.JUnitTestClassIdentifierTest
Running org.pitest.junit.ParameterisedJUnitTestFinderTest
Tests run: 2, Failures: 0, Errors: 0, Skipped: 0, Time elapsed: 0.003 sec - in org.pitest.junit.ParameterisedJUnitTestFinderTest
Running org.pitest.junit.TestInfoTest
Tests run: 5, Failures: 0, Errors: 0, Skipped: 0, Time elapsed: 0.004 sec - in org.pitest.junit.TestInfoTest
Running org.pitest.testapi.execute.MultipleTestGroupTest
Tests run: 3, Failures: 0, Errors: 0, Skipped: 0, Time elapsed: 0.038 sec - in org.pitest.testapi.execute.MultipleTestGroupTest
Running org.pitest.testapi.execute.TestPitest
Tests run: 12, Failures: 0, Errors: 0, Skipped: 0, Time elapsed: 0.025 sec - in org.pitest.testapi.execute.TestPitest
Running org.pitest.testapi.execute.ResultTypeTest
Tests run: 4, Failures: 0, Errors: 0, Skipped: 0, Time elapsed: 0.01 sec - in org.pitest.testapi.execute.ResultTypeTest
Running org.pitest.testapi.execute.ExitingResultCollectorTest
Tests run: 5, Failures: 0, Errors: 0, Skipped: 0, Time elapsed: 0.002 sec - in org.pitest.testapi.execute.ExitingResultCollectorTest
Running org.pitest.testapi.DescriptionTest
Tests run: 1, Failures: 0, Errors: 0, Skipped: 0, Time elapsed: 0.001 sec - in org.pitest.testapi.DescriptionTest
Running org.pitest.util.SafeDataInputStreamTest
Tests run: 1, Failures: 0, Errors: 0, Skipped: 0, Time elapsed: 0.001 sec - in org.pitest.util.SafeDataInputStreamTest
Running org.pitest.util.FunctionsTest
Tests run: 6, Failures: 0, Errors: 0, Skipped: 0, Time elapsed: 0.012 sec - in org.pitest.util.FunctionsTest
Running org.pitest.util.GlobTest
Tests run: 10, Failures: 0, Errors: 0, Skipped: 0, Time elapsed: 0 sec - in org.pitest.util.GlobTest
Running org.pitest.util.IsolationUtilsTest
Tests run: 4, Failures: 0, Errors: 0, Skipped: 0, Time elapsed: 0.021 sec - in org.pitest.util.IsolationUtilsTest
Running org.pitest.util.StreamUtilTest
Tests run: 2, Failures: 0, Errors: 0, Skipped: 0, Time elapsed: 0.001 sec - in org.pitest.util.StreamUtilTest
Running org.pitest.util.MemoryMonitorTest

DUMPING MEMORY INFO

Heap Memory Usage: init = 73400320(71680K) used = 132090656(128994K) committed = 203534336(198764K) max = 1131216896(1104704K)
Non-Heap Memory Usage: init = 2555904(2496K) used = 44200560(43164K) committed = 53805056(52544K) max = -1(-1K)

Name: Copy
Collection count: 57
Collection time: 387
Memory Pools: 
	Eden Space
	Survivor Space

Name: MarkSweepCompact
Collection count: 2
Collection time: 321
Memory Pools: 
	Eden Space
	Survivor Space
	Tenured Gen
Memory Pools Info

Name: Code Cache
Usage: init = 2555904(2496K) used = 11796736(11520K) committed = 11862016(11584K) max = 251658240(245760K)
Collection Usage: null
Peak Usage: init = 2555904(2496K) used = 11796736(11520K) committed = 11862016(11584K) max = 251658240(245760K)
Type: Non-heap memory
Memory Manager Names: 
	CodeCacheManager



Name: Metaspace
Usage: init = 0(0K) used = 28652280(27980K) committed = 35651584(34816K) max = -1(-1K)
Collection Usage: null
Peak Usage: init = 0(0K) used = 28652280(27980K) committed = 35651584(34816K) max = -1(-1K)
Type: Non-heap memory
Memory Manager Names: 
	Metaspace Manager



Name: Compressed Class Space
Usage: init = 0(0K) used = 3805832(3716K) committed = 6291456(6144K) max = 1073741824(1048576K)
Collection Usage: null
Peak Usage: init = 0(0K) used = 3805832(3716K) committed = 6291456(6144K) max = 1073741824(1048576K)
Type: Non-heap memory
Memory Manager Names: 
	Metaspace Manager



Name: Eden Space
Usage: init = 19595264(19136K) used = 31510296(30771K) committed = 56164352(54848K) max = 312082432(304768K)
Collection Usage: init = 19595264(19136K) used = 0(0K) committed = 56164352(54848K) max = 312082432(304768K)
Peak Usage: init = 19595264(19136K) used = 56164352(54848K) committed = 56164352(54848K) max = 312082432(304768K)
Type: Heap memory
Memory Manager Names: 
	MarkSweepCompact
	Copy



Name: Survivor Space
Usage: init = 2424832(2368K) used = 4359560(4257K) committed = 7012352(6848K) max = 38993920(38080K)
Collection Usage: init = 2424832(2368K) used = 4359560(4257K) committed = 7012352(6848K) max = 38993920(38080K)
Peak Usage: init = 2424832(2368K) used = 7012352(6848K) committed = 7012352(6848K) max = 38993920(38080K)
Type: Heap memory
Memory Manager Names: 
	MarkSweepCompact
	Copy



Name: Tenured Gen
Usage: init = 48955392(47808K) used = 96220800(93965K) committed = 140357632(137068K) max = 780140544(761856K)
Collection Usage: init = 48955392(47808K) used = 84213744(82239K) committed = 84213760(82240K) max = 780140544(761856K)
Peak Usage: init = 48955392(47808K) used = 96220800(93965K) committed = 140357632(137068K) max = 780140544(761856K)
Type: Heap memory
Memory Manager Names: 
	MarkSweepCompact


Tests run: 1, Failures: 0, Errors: 0, Skipped: 0, Time elapsed: 0.012 sec - in org.pitest.util.MemoryMonitorTest
Running org.pitest.util.StringUtilTest
Tests run: 4, Failures: 0, Errors: 0, Skipped: 0, Time elapsed: 0.001 sec - in org.pitest.util.StringUtilTest
Running org.pitest.util.CachingByteArraySourceTest
Tests run: 2, Failures: 0, Errors: 0, Skipped: 0, Time elapsed: 0.001 sec - in org.pitest.util.CachingByteArraySourceTest
Running org.pitest.functional.predicate.TrueTest
Tests run: 1, Failures: 0, Errors: 0, Skipped: 0, Time elapsed: 0.001 sec - in org.pitest.functional.predicate.TrueTest
Running org.pitest.functional.predicate.OrTest
Tests run: 6, Failures: 0, Errors: 0, Skipped: 0, Time elapsed: 0.001 sec - in org.pitest.functional.predicate.OrTest
Running org.pitest.functional.predicate.NotTest
Tests run: 2, Failures: 0, Errors: 0, Skipped: 0, Time elapsed: 0 sec - in org.pitest.functional.predicate.NotTest
Running org.pitest.functional.predicate.AndTest
Tests run: 6, Failures: 0, Errors: 0, Skipped: 0, Time elapsed: 0.001 sec - in org.pitest.functional.predicate.AndTest
Running org.pitest.functional.predicate.FalseTest
Tests run: 1, Failures: 0, Errors: 0, Skipped: 0, Time elapsed: 0 sec - in org.pitest.functional.predicate.FalseTest
Running org.pitest.functional.FCollectionTest
Tests run: 18, Failures: 0, Errors: 0, Skipped: 0, Time elapsed: 0.004 sec - in org.pitest.functional.FCollectionTest
Running org.pitest.functional.prelude.PreludeTest
Tests run: 5, Failures: 0, Errors: 0, Skipped: 0, Time elapsed: 0.045 sec - in org.pitest.functional.prelude.PreludeTest
Running org.pitest.functional.MutableListTest
Tests run: 29, Failures: 0, Errors: 0, Skipped: 0, Time elapsed: 0.024 sec - in org.pitest.functional.MutableListTest
Running org.pitest.functional.OptionTest
Tests run: 21, Failures: 0, Errors: 0, Skipped: 0, Time elapsed: 0.128 sec - in org.pitest.functional.OptionTest
Running org.pitest.functional.FArrayTest
Tests run: 9, Failures: 0, Errors: 0, Skipped: 0, Time elapsed: 0.002 sec - in org.pitest.functional.FArrayTest
Running org.pitest.help.PitHelpErrorTest
Tests run: 1, Failures: 0, Errors: 0, Skipped: 0, Time elapsed: 0 sec - in org.pitest.help.PitHelpErrorTest
Running org.pitest.coverage.TestInfoTest
Tests run: 1, Failures: 0, Errors: 0, Skipped: 0, Time elapsed: 0.052 sec - in org.pitest.coverage.TestInfoTest
Running org.pitest.coverage.codeassist.CoverageClassVisitorTest
Tests run: 1, Failures: 0, Errors: 0, Skipped: 0, Time elapsed: 0.01 sec - in org.pitest.coverage.codeassist.CoverageClassVisitorTest
Running org.pitest.coverage.codeassist.LineMapperTest
Tests run: 6, Failures: 0, Errors: 0, Skipped: 0, Time elapsed: 0.022 sec - in org.pitest.coverage.codeassist.LineMapperTest
Running org.pitest.coverage.execute.DependencyFilterTest
Tests run: 3, Failures: 0, Errors: 0, Skipped: 0, Time elapsed: 0.005 sec - in org.pitest.coverage.execute.DependencyFilterTest
Running org.pitest.coverage.analysis.BlockTest
Tests run: 1, Failures: 0, Errors: 0, Skipped: 0, Time elapsed: 0.033 sec - in org.pitest.coverage.analysis.BlockTest
Running org.pitest.coverage.BlockLocationTest
Tests run: 1, Failures: 0, Errors: 0, Skipped: 0, Time elapsed: 0.026 sec - in org.pitest.coverage.BlockLocationTest
Running org.pitest.coverage.CoverageResultTest
Tests run: 3, Failures: 0, Errors: 0, Skipped: 0, Time elapsed: 0.001 sec - in org.pitest.coverage.CoverageResultTest
Running org.pitest.coverage.CoverageTransformerTest
Tests run: 3, Failures: 0, Errors: 0, Skipped: 0, Time elapsed: 0.427 sec - in org.pitest.coverage.CoverageTransformerTest
Running org.pitest.coverage.ClassLineTest
Tests run: 1, Failures: 0, Errors: 0, Skipped: 0, Time elapsed: 0.027 sec - in org.pitest.coverage.ClassLineTest
Running org.pitest.coverage.TestInfoNameComparatorTest
Tests run: 2, Failures: 0, Errors: 0, Skipped: 0, Time elapsed: 0.003 sec - in org.pitest.coverage.TestInfoNameComparatorTest
Running org.pitest.classinfo.RepositoryTest
Tests run: 26, Failures: 0, Errors: 0, Skipped: 0, Time elapsed: 0.041 sec - in org.pitest.classinfo.RepositoryTest
Running org.pitest.classinfo.ClassInfoVisitorTest
Tests run: 8, Failures: 0, Errors: 0, Skipped: 0, Time elapsed: 0.005 sec - in org.pitest.classinfo.ClassInfoVisitorTest
Running org.pitest.classinfo.ClassIdentifierTest
Tests run: 1, Failures: 0, Errors: 0, Skipped: 0, Time elapsed: 0.03 sec - in org.pitest.classinfo.ClassIdentifierTest
Running org.pitest.classinfo.AddlerHashTest
Tests run: 3, Failures: 0, Errors: 0, Skipped: 0, Time elapsed: 0.004 sec - in org.pitest.classinfo.AddlerHashTest
Running org.pitest.classinfo.TestToClassMapperTest
Tests run: 3, Failures: 0, Errors: 0, Skipped: 0, Time elapsed: 0.001 sec - in org.pitest.classinfo.TestToClassMapperTest
Running org.pitest.classinfo.ComputeClassWriterTest
Tests run: 10, Failures: 0, Errors: 0, Skipped: 0, Time elapsed: 0.019 sec - in org.pitest.classinfo.ComputeClassWriterTest
Running org.pitest.classinfo.HierarchicalClassIdTest
Tests run: 1, Failures: 0, Errors: 0, Skipped: 0, Time elapsed: 0.023 sec - in org.pitest.classinfo.HierarchicalClassIdTest
Running org.pitest.classinfo.ClassNameTest
Tests run: 22, Failures: 0, Errors: 0, Skipped: 0, Time elapsed: 0.044 sec - in org.pitest.classinfo.ClassNameTest
Running org.pitest.classinfo.NameToClassInfoTest
Tests run: 1, Failures: 0, Errors: 0, Skipped: 0, Time elapsed: 0.004 sec - in org.pitest.classinfo.NameToClassInfoTest
Running org.pitest.classinfo.ClassInfoTest
Tests run: 7, Failures: 0, Errors: 0, Skipped: 0, Time elapsed: 0.022 sec - in org.pitest.classinfo.ClassInfoTest
Running org.pitest.classpath.OtherClassLoaderClassPathRootTest
Tests run: 3, Failures: 0, Errors: 0, Skipped: 0, Time elapsed: 0 sec - in org.pitest.classpath.OtherClassLoaderClassPathRootTest
Running org.pitest.classpath.CompoundClassPathRootTest
Tests run: 6, Failures: 0, Errors: 0, Skipped: 0, Time elapsed: 0.003 sec - in org.pitest.classpath.CompoundClassPathRootTest
Running org.pitest.classpath.ClassPathTest
Tests run: 4, Failures: 0, Errors: 0, Skipped: 0, Time elapsed: 0.003 sec - in org.pitest.classpath.ClassPathTest
Running org.pitest.classpath.DirectoryClassPathRootTest
Tests run: 2, Failures: 0, Errors: 0, Skipped: 0, Time elapsed: 0.007 sec - in org.pitest.classpath.DirectoryClassPathRootTest
Running org.pitest.classpath.CodeSourceTest
Tests run: 11, Failures: 0, Errors: 0, Skipped: 0, Time elapsed: 0.013 sec - in org.pitest.classpath.CodeSourceTest
Running org.pitest.classpath.ArchiveClassPathRootTest
Tests run: 6, Failures: 0, Errors: 0, Skipped: 0, Time elapsed: 0.002 sec - in org.pitest.classpath.ArchiveClassPathRootTest
Running org.pitest.testng.TestNGAdapterTest
Tests run: 5, Failures: 0, Errors: 0, Skipped: 0, Time elapsed: 0.026 sec - in org.pitest.testng.TestNGAdapterTest
Running org.pitest.testng.TestNGTestUnitTest
[TestNG] Running:
  com.example.testng.HasGroups


===============================================
com.example.testng.HasGroups
Total tests run: 2, Failures: 0, Skips: 0
===============================================

[TestNG] Running:
  com.example.testng.Fails


===============================================
com.example.testng.Fails
Total tests run: 2, Failures: 1, Skips: 1
===============================================

[TestNG] Running:
  com.example.testng.Passes


===============================================
com.example.testng.Passes
Total tests run: 1, Failures: 0, Skips: 0
===============================================

[TestNG] Running:
  com.example.testng.HasGroups


===============================================
com.example.testng.HasGroups
Total tests run: 2, Failures: 0, Skips: 0
===============================================

[TestNG] Running:
  com.example.testng.Passes


===============================================
com.example.testng.Passes
Total tests run: 1, Failures: 0, Skips: 0
===============================================

[TestNG] Running:
  com.example.testng.Passes


===============================================
com.example.testng.Passes
Total tests run: 1, Failures: 0, Skips: 0
===============================================

[TestNG] Running:
  com.example.testng.Passes


===============================================
com.example.testng.Passes
Total tests run: 1, Failures: 0, Skips: 0
===============================================

[TestNG] Running:
  com.example.testng.Fails


===============================================
com.example.testng.Fails
Total tests run: 2, Failures: 1, Skips: 1
===============================================

[TestNG] Running:
  com.example.testng.Passes


===============================================
com.example.testng.Passes
Total tests run: 1, Failures: 0, Skips: 0
===============================================

[TestNG] Running:
  com.example.testng.Fails


===============================================
com.example.testng.Fails
Total tests run: 2, Failures: 1, Skips: 1
===============================================

[TestNG] Running:
  com.example.testng.Fails


===============================================
com.example.testng.Fails
Total tests run: 2, Failures: 1, Skips: 1
===============================================

[TestNG] Running:
  com.example.testng.Passes


===============================================
com.example.testng.Passes
Total tests run: 1, Failures: 0, Skips: 0
===============================================

[TestNG] Running:
  com.example.testng.Fails


===============================================
com.example.testng.Fails
Total tests run: 2, Failures: 1, Skips: 1
===============================================

[TestNG] Running:
  com.example.testng.Passes


===============================================
com.example.testng.Passes
Total tests run: 1, Failures: 0, Skips: 0
===============================================

[TestNG] Running:
  com.example.testng.Skips


===============================================
com.example.testng.Skips
Total tests run: 1, Failures: 0, Skips: 1
===============================================

[TestNG] Running:
  com.example.testng.Skips


===============================================
com.example.testng.Skips
Total tests run: 1, Failures: 0, Skips: 1
===============================================

Tests run: 15, Failures: 0, Errors: 0, Skipped: 0, Time elapsed: 0.254 sec - in org.pitest.testng.TestNGTestUnitTest
Running org.pitest.testng.TestNGTestClassIdentifierTest
Tests run: 4, Failures: 0, Errors: 0, Skipped: 0, Time elapsed: 0.014 sec - in org.pitest.testng.TestNGTestClassIdentifierTest
Running org.pitest.testng.TestNGTestUnitFinderTest
Tests run: 4, Failures: 0, Errors: 0, Skipped: 0, Time elapsed: 0.001 sec - in org.pitest.testng.TestNGTestUnitFinderTest
Running org.pitest.testng.TestNGConfigurationTest
Tests run: 1, Failures: 0, Errors: 0, Skipped: 0, Time elapsed: 0.001 sec - in org.pitest.testng.TestNGConfigurationTest
Running org.pitest.sequence.MatchTest
Tests run: 6, Failures: 0, Errors: 0, Skipped: 0, Time elapsed: 0.002 sec - in org.pitest.sequence.MatchTest
Running org.pitest.sequence.SequenceQueryTest
Tests run: 7, Failures: 0, Errors: 0, Skipped: 0, Time elapsed: 0.003 sec - in org.pitest.sequence.SequenceQueryTest
Running org.pitest.dependency.DependencyAccessTest
Tests run: 1, Failures: 0, Errors: 0, Skipped: 0, Time elapsed: 0.038 sec - in org.pitest.dependency.DependencyAccessTest
Running org.pitest.dependency.DependencyExtractorTest
Tests run: 6, Failures: 0, Errors: 0, Skipped: 0, Time elapsed: 0.063 sec - in org.pitest.dependency.DependencyExtractorTest
Running org.pitest.dependency.IgnoreCoreClassesTest
Tests run: 7, Failures: 0, Errors: 0, Skipped: 0, Time elapsed: 0.003 sec - in org.pitest.dependency.IgnoreCoreClassesTest
Running org.pitest.dependency.DependencyClassVisitorTest
Tests run: 3, Failures: 0, Errors: 0, Skipped: 0, Time elapsed: 0.018 sec - in org.pitest.dependency.DependencyClassVisitorTest
Running org.pitest.TestJUnitConfiguration
1
> 1
2
> 2
3
> 3
[AdaptedJUnitTestUnit [clazz=class org.pitest.TestJUnitConfiguration$MarkerTest1, filter=Some(one(org.pitest.TestJUnitConfiguration$MarkerTest1))], AdaptedJUnitTestUnit [clazz=class org.pitest.TestJUnitConfiguration$MarkerTest1, filter=Some(two(org.pitest.TestJUnitConfiguration$MarkerTest1))], AdaptedJUnitTestUnit [clazz=class org.pitest.TestJUnitConfiguration$MarkerTest2, filter=Some(one(org.pitest.TestJUnitConfiguration$MarkerTest2))], AdaptedJUnitTestUnit [clazz=class org.pitest.TestJUnitConfiguration$MarkerTest2, filter=Some(two(org.pitest.TestJUnitConfiguration$MarkerTest2))]]
Tests run: 25, Failures: 0, Errors: 0, Skipped: 0, Time elapsed: 0.138 sec - in org.pitest.TestJUnitConfiguration
Running org.pitest.reflection.ReflectionTest
Tests run: 4, Failures: 0, Errors: 0, Skipped: 0, Time elapsed: 0 sec - in org.pitest.reflection.ReflectionTest
Running org.pitest.TestResultTest
Tests run: 1, Failures: 0, Errors: 0, Skipped: 0, Time elapsed: 0 sec - in org.pitest.TestResultTest

Results :

Tests run: 977, Failures: 0, Errors: 0, Skipped: 4

[INFO]                                                                         
[INFO] ------------------------------------------------------------------------
[INFO] Building pitest-entry 1.2.1-SNAPSHOT
[INFO] ------------------------------------------------------------------------
[INFO] 
[INFO] --- maven-checkstyle-plugin:2.15:check (checkstyle) @ pitest-entry ---
[INFO] 
[INFO] --- maven-resources-plugin:2.6:resources (default-resources) @ pitest-entry ---
[INFO] Using 'UTF-8' encoding to copy filtered resources.
[INFO] Copying 2 resources
[INFO] 
[INFO] --- maven-compiler-plugin:3.1:compile (default-compile) @ pitest-entry ---
[INFO] Nothing to compile - all classes are up to date
[INFO] 
[INFO] --- maven-resources-plugin:2.6:testResources (default-testResources) @ pitest-entry ---
[INFO] Using 'UTF-8' encoding to copy filtered resources.
[INFO] Copying 10 resources
[INFO] 
[INFO] --- maven-compiler-plugin:3.1:testCompile (default-testCompile) @ pitest-entry ---
[INFO] Nothing to compile - all classes are up to date
[INFO] 
[INFO] --- maven-surefire-plugin:2.17:test (default-test) @ pitest-entry ---
[INFO] Surefire report directory: /scratch/dginelli/workspace/repairnator-repairnator-experiments-hcoles-pitest-247833128-20170628-100234_bugonly-firstCommit/pitest-entry/target/surefire-reports
[INFO] Using configured provider org.apache.maven.surefire.junitcore.JUnitCoreProvider
[INFO] parallel='none', perCoreThreadCount=true, threadCount=0, useUnlimitedThreads=false, threadCountSuites=0, threadCountClasses=0, threadCountMethods=0, parallelOptimized=true

-------------------------------------------------------
 T E S T S
-------------------------------------------------------
Running org.pitest.process.WrappingProcessTest
Tests run: 1, Failures: 0, Errors: 0, Skipped: 0, Time elapsed: 0.694 sec - in org.pitest.process.WrappingProcessTest
Running org.pitest.process.KnownLocationJavaExecutableLocatorTest
Tests run: 1, Failures: 0, Errors: 0, Skipped: 0, Time elapsed: 0.006 sec - in org.pitest.process.KnownLocationJavaExecutableLocatorTest
Running org.pitest.mutationtest.statistics.MutationStatisticsPrecursorTest
Tests run: 12, Failures: 0, Errors: 0, Skipped: 0, Time elapsed: 0.1 sec - in org.pitest.mutationtest.statistics.MutationStatisticsPrecursorTest
Running org.pitest.mutationtest.statistics.MutationStatisticsListenerTest
Tests run: 1, Failures: 0, Errors: 0, Skipped: 0, Time elapsed: 0.007 sec - in org.pitest.mutationtest.statistics.MutationStatisticsListenerTest
Running org.pitest.mutationtest.statistics.ScoreTest
Tests run: 13, Failures: 0, Errors: 0, Skipped: 0, Time elapsed: 0.01 sec - in org.pitest.mutationtest.statistics.ScoreTest
Running org.pitest.mutationtest.config.CompoundListenerFactoryTest
Tests run: 1, Failures: 0, Errors: 0, Skipped: 0, Time elapsed: 0.217 sec - in org.pitest.mutationtest.config.CompoundListenerFactoryTest
Running org.pitest.mutationtest.config.CompoundTestListenerTest
Tests run: 3, Failures: 0, Errors: 0, Skipped: 0, Time elapsed: 0.004 sec - in org.pitest.mutationtest.config.CompoundTestListenerTest
Running org.pitest.mutationtest.config.SettingsFactoryTest
Tests run: 12, Failures: 0, Errors: 0, Skipped: 1, Time elapsed: 0.344 sec - in org.pitest.mutationtest.config.SettingsFactoryTest
Running org.pitest.mutationtest.config.DefaultDependencyPathPredicateTest
Tests run: 2, Failures: 0, Errors: 0, Skipped: 0, Time elapsed: 0.002 sec - in org.pitest.mutationtest.config.DefaultDependencyPathPredicateTest
Running org.pitest.mutationtest.config.PluginServicesTest
Tests run: 3, Failures: 0, Errors: 0, Skipped: 0, Time elapsed: 0.015 sec - in org.pitest.mutationtest.config.PluginServicesTest
Running org.pitest.mutationtest.config.DefaultCodePathPredicateTest
Tests run: 5, Failures: 0, Errors: 0, Skipped: 0, Time elapsed: 0.003 sec - in org.pitest.mutationtest.config.DefaultCodePathPredicateTest
Running org.pitest.mutationtest.config.ReportOptionsTest
Tests run: 1, Failures: 0, Errors: 0, Skipped: 0, Time elapsed: 0 sec - in org.pitest.mutationtest.config.ReportOptionsTest
Running org.pitest.mutationtest.config.PathNamePredicateTest
Tests run: 2, Failures: 0, Errors: 0, Skipped: 0, Time elapsed: 0.004 sec - in org.pitest.mutationtest.config.PathNamePredicateTest
Running org.pitest.mutationtest.build.intercept.annotations.ExcludedAnnotationInterceptorTest
Tests run: 5, Failures: 0, Errors: 0, Skipped: 0, Time elapsed: 0.08 sec - in org.pitest.mutationtest.build.intercept.annotations.ExcludedAnnotationInterceptorTest
Running org.pitest.mutationtest.build.intercept.logging.LoggingCallsFilterTest
Tests run: 4, Failures: 0, Errors: 0, Skipped: 0, Time elapsed: 0.043 sec - in org.pitest.mutationtest.build.intercept.logging.LoggingCallsFilterTest
Running org.pitest.mutationtest.build.intercept.timeout.SimpleInfiniteLoopInterceptorTest
found counter at 3
found counter at 3
found counter at 3
found counter at 3
found counter at 3
found counter at 12
found counter at 37
found counter at 12
found counter at 38
found counter at 23
found counter at 23
found counter at 18
found counter at 8
broken by store at 85
broken by store at 85
found counter at 85
found counter at 3
found counter at 3
broken by store at 27
found counter at 3
found counter at 3
found counter at 3
found counter at 3
broken by store at 31
found counter at 3
found counter at 3
broken by store at 26
found counter at 3
found counter at 3
found counter at 3
found counter at 3
found counter at 3
found counter at 3
found counter at 3
Tests run: 20, Failures: 1, Errors: 0, Skipped: 3, Time elapsed: 0.134 sec <<< FAILURE! - in org.pitest.mutationtest.build.intercept.timeout.SimpleInfiniteLoopInterceptorTest
shouldMatchRealInfiniteLoopFromJodaTimeMutants(org.pitest.mutationtest.build.intercept.timeout.SimpleInfiniteLoopInterceptorTest)  Time elapsed: 0.028 sec  <<< FAILURE!
org.junit.ComparisonFailure: [With javac compiler did not match as expected Byte code is 
   L0
    LINENUMBER 183 L0
    ALOAD 1
    INVOKEINTERFACE org/joda/time/ReadablePartial.size ()I
    ISTORE 3
   L1
    LINENUMBER 184 L1
    ICONST_0
    ISTORE 4
   L2
    GOTO L3
   L4
    LINENUMBER 185 L4
    ALOAD 2
    ILOAD 4
    IALOAD
    ISTORE 5
   L5
    LINENUMBER 186 L5
    ALOAD 1
    ILOAD 4
    INVOKEINTERFACE org/joda/time/ReadablePartial.getField (I)Lorg/joda/time/DateTimeField;
    ASTORE 6
   L6
    LINENUMBER 187 L6
    ILOAD 5
    ALOAD 6
    INVOKEVIRTUAL org/joda/time/DateTimeField.getMinimumValue ()I
    IF_ICMPGE L7
   L8
    LINENUMBER 188 L8
    NEW org/joda/time/IllegalFieldValueException
    DUP
   L9
    LINENUMBER 189 L9
    ALOAD 6
    INVOKEVIRTUAL org/joda/time/DateTimeField.getType ()Lorg/joda/time/DateTimeFieldType;
    ILOAD 5
    INVOKESTATIC java/lang/Integer.valueOf (I)Ljava/lang/Integer;
   L10
    LINENUMBER 190 L10
    ALOAD 6
    INVOKEVIRTUAL org/joda/time/DateTimeField.getMinimumValue ()I
    INVOKESTATIC java/lang/Integer.valueOf (I)Ljava/lang/Integer;
    ACONST_NULL
   L11
    LINENUMBER 188 L11
    INVOKESPECIAL org/joda/time/IllegalFieldValueException.<init> (Lorg/joda/time/DateTimeFieldType;Ljava/lang/Number;Ljava/lang/Number;Ljava/lang/Number;)V
    ATHROW
   L7
    LINENUMBER 192 L7
    ILOAD 5
    ALOAD 6
    INVOKEVIRTUAL org/joda/time/DateTimeField.getMaximumValue ()I
    IF_ICMPLE L12
   L13
    LINENUMBER 193 L13
    NEW org/joda/time/IllegalFieldValueException
    DUP
   L14
    LINENUMBER 194 L14
    ALOAD 6
    INVOKEVIRTUAL org/joda/time/DateTimeField.getType ()Lorg/joda/time/DateTimeFieldType;
    ILOAD 5
    INVOKESTATIC java/lang/Integer.valueOf (I)Ljava/lang/Integer;
   L15
    LINENUMBER 195 L15
    ACONST_NULL
    ALOAD 6
    INVOKEVIRTUAL org/joda/time/DateTimeField.getMaximumValue ()I
    INVOKESTATIC java/lang/Integer.valueOf (I)Ljava/lang/Integer;
   L16
    LINENUMBER 193 L16
    INVOKESPECIAL org/joda/time/IllegalFieldValueException.<init> (Lorg/joda/time/DateTimeFieldType;Ljava/lang/Number;Ljava/lang/Number;Ljava/lang/Number;)V
    ATHROW
   L12
    LINENUMBER 184 L12
    NOP
   L3
    ILOAD 4
    ILOAD 3
    IF_ICMPLT L4
   L17
    LINENUMBER 199 L17
    ICONST_0
    ISTORE 4
   L18
    GOTO L19
   L20
    LINENUMBER 200 L20
    ALOAD 2
    ILOAD 4
    IALOAD
    ISTORE 5
   L21
    LINENUMBER 201 L21
    ALOAD 1
    ILOAD 4
    INVOKEINTERFACE org/joda/time/ReadablePartial.getField (I)Lorg/joda/time/DateTimeField;
    ASTORE 6
   L22
    LINENUMBER 202 L22
    ILOAD 5
    ALOAD 6
    ALOAD 1
    ALOAD 2
    INVOKEVIRTUAL org/joda/time/DateTimeField.getMinimumValue (Lorg/joda/time/ReadablePartial;[I)I
    IF_ICMPGE L23
   L24
    LINENUMBER 203 L24
    NEW org/joda/time/IllegalFieldValueException
    DUP
   L25
    LINENUMBER 204 L25
    ALOAD 6
    INVOKEVIRTUAL org/joda/time/DateTimeField.getType ()Lorg/joda/time/DateTimeFieldType;
    ILOAD 5
    INVOKESTATIC java/lang/Integer.valueOf (I)Ljava/lang/Integer;
   L26
    LINENUMBER 205 L26
    ALOAD 6
    ALOAD 1
    ALOAD 2
    INVOKEVIRTUAL org/joda/time/DateTimeField.getMinimumValue (Lorg/joda/time/ReadablePartial;[I)I
    INVOKESTATIC java/lang/Integer.valueOf (I)Ljava/lang/Integer;
    ACONST_NULL
   L27
    LINENUMBER 203 L27
    INVOKESPECIAL org/joda/time/IllegalFieldValueException.<init> (Lorg/joda/time/DateTimeFieldType;Ljava/lang/Number;Ljava/lang/Number;Ljava/lang/Number;)V
    ATHROW
   L23
    LINENUMBER 207 L23
    ILOAD 5
    ALOAD 6
    ALOAD 1
    ALOAD 2
    INVOKEVIRTUAL org/joda/time/DateTimeField.getMaximumValue (Lorg/joda/time/ReadablePartial;[I)I
    IF_ICMPLE L28
   L29
    LINENUMBER 208 L29
    NEW org/joda/time/IllegalFieldValueException
    DUP
   L30
    LINENUMBER 209 L30
    ALOAD 6
    INVOKEVIRTUAL org/joda/time/DateTimeField.getType ()Lorg/joda/time/DateTimeFieldType;
    ILOAD 5
    INVOKESTATIC java/lang/Integer.valueOf (I)Ljava/lang/Integer;
   L31
    LINENUMBER 210 L31
    ACONST_NULL
    ALOAD 6
    ALOAD 1
    ALOAD 2
    INVOKEVIRTUAL org/joda/time/DateTimeField.getMaximumValue (Lorg/joda/time/ReadablePartial;[I)I
    INVOKESTATIC java/lang/Integer.valueOf (I)Ljava/lang/Integer;
   L32
    LINENUMBER 208 L32
    INVOKESPECIAL org/joda/time/IllegalFieldValueException.<init> (Lorg/joda/time/DateTimeFieldType;Ljava/lang/Number;Ljava/lang/Number;Ljava/lang/Number;)V
    ATHROW
   L28
    LINENUMBER 199 L28
    IINC 4 1
   L19
    ILOAD 4
    ILOAD 3
    IF_ICMPLT L20
   L33
    LINENUMBER 213 L33
    RETURN
   L34
    LOCALVARIABLE this Lorg/joda/time/chrono/BaseChronology; L0 L34 0
    LOCALVARIABLE partial Lorg/joda/time/ReadablePartial; L0 L34 1
    LOCALVARIABLE values [I L0 L34 2
    LOCALVARIABLE size I L1 L34 3
    LOCALVARIABLE i I L2 L17 4
    LOCALVARIABLE value I L5 L12 5
    LOCALVARIABLE field Lorg/joda/time/DateTimeField; L6 L12 6
    LOCALVARIABLE i I L18 L33 4
    LOCALVARIABLE value I L21 L28 5
    LOCALVARIABLE field Lorg/joda/time/DateTimeField; L22 L28 6
    MAXSTACK = 8
    MAXLOCALS = 7
] expected:<[tru]e> but was:<[fals]e>
	at sun.reflect.NativeConstructorAccessorImpl.newInstance0(Native Method)
	at sun.reflect.NativeConstructorAccessorImpl.newInstance(NativeConstructorAccessorImpl.java:62)
	at sun.reflect.DelegatingConstructorAccessorImpl.newInstance(DelegatingConstructorAccessorImpl.java:45)
	at org.pitest.mutationtest.build.intercept.timeout.SimpleInfiniteLoopInterceptorTest.checkFiltered(SimpleInfiniteLoopInterceptorTest.java:214)
	at org.pitest.mutationtest.build.intercept.timeout.SimpleInfiniteLoopInterceptorTest.shouldMatchRealInfiniteLoopFromJodaTimeMutants(SimpleInfiniteLoopInterceptorTest.java:172)

Running org.pitest.mutationtest.build.intercept.javafeatures.TryWithResourcesFilterTest
Tests run: 6, Failures: 0, Errors: 0, Skipped: 0, Time elapsed: 0.052 sec - in org.pitest.mutationtest.build.intercept.javafeatures.TryWithResourcesFilterTest
Running org.pitest.mutationtest.build.intercept.javafeatures.InlinedFinallyBlockFilterTest
Tests run: 5, Failures: 0, Errors: 0, Skipped: 0, Time elapsed: 0.004 sec - in org.pitest.mutationtest.build.intercept.javafeatures.InlinedFinallyBlockFilterTest
Running org.pitest.mutationtest.build.intercept.staticinitializers.StaticInitializerFilterTest
Tests run: 2, Failures: 0, Errors: 0, Skipped: 0, Time elapsed: 0.002 sec - in org.pitest.mutationtest.build.intercept.staticinitializers.StaticInitializerFilterTest
Running org.pitest.mutationtest.build.intercept.staticinitializers.StaticInitializerInterceptorTest
Tests run: 6, Failures: 0, Errors: 0, Skipped: 0, Time elapsed: 0.02 sec - in org.pitest.mutationtest.build.intercept.staticinitializers.StaticInitializerInterceptorTest
Running org.pitest.mutationtest.build.AnalyisPriorityComparatorTest
Tests run: 2, Failures: 0, Errors: 0, Skipped: 0, Time elapsed: 0 sec - in org.pitest.mutationtest.build.AnalyisPriorityComparatorTest
Running org.pitest.mutationtest.build.DefaultTestPrioritiserTest
Tests run: 3, Failures: 0, Errors: 0, Skipped: 0, Time elapsed: 0.032 sec - in org.pitest.mutationtest.build.DefaultTestPrioritiserTest
Running org.pitest.mutationtest.build.MutationDiscoveryTest
Tests run: 12, Failures: 0, Errors: 0, Skipped: 0, Time elapsed: 0.124 sec - in org.pitest.mutationtest.build.MutationDiscoveryTest
Running org.pitest.mutationtest.build.DefaultGrouperTest
Tests run: 3, Failures: 0, Errors: 0, Skipped: 0, Time elapsed: 0.002 sec - in org.pitest.mutationtest.build.DefaultGrouperTest
Running org.pitest.mutationtest.build.MutationTestBuilderTest
Tests run: 5, Failures: 0, Errors: 0, Skipped: 0, Time elapsed: 0.015 sec - in org.pitest.mutationtest.build.MutationTestBuilderTest
Running org.pitest.mutationtest.build.KnownStatusMutationTestUnitTest
Tests run: 2, Failures: 0, Errors: 0, Skipped: 0, Time elapsed: 0.001 sec - in org.pitest.mutationtest.build.KnownStatusMutationTestUnitTest
Running org.pitest.mutationtest.build.TestInfoPriorisationComparatorTest
Tests run: 3, Failures: 0, Errors: 0, Skipped: 0, Time elapsed: 0.014 sec - in org.pitest.mutationtest.build.TestInfoPriorisationComparatorTest
Running org.pitest.mutationtest.build.MutationSourceTest
Tests run: 2, Failures: 0, Errors: 0, Skipped: 0, Time elapsed: 0.007 sec - in org.pitest.mutationtest.build.MutationSourceTest
Running org.pitest.mutationtest.build.MutationTestUnitTest
Tests run: 2, Failures: 0, Errors: 0, Skipped: 0, Time elapsed: 0.043 sec - in org.pitest.mutationtest.build.MutationTestUnitTest
Running org.pitest.mutationtest.build.CompoundMutationInterceptorTest
Tests run: 3, Failures: 0, Errors: 0, Skipped: 0, Time elapsed: 0.009 sec - in org.pitest.mutationtest.build.CompoundMutationInterceptorTest
Running org.pitest.mutationtest.incremental.FileWriterFactoryTest
Tests run: 3, Failures: 0, Errors: 0, Skipped: 0, Time elapsed: 0.038 sec - in org.pitest.mutationtest.incremental.FileWriterFactoryTest
Running org.pitest.mutationtest.incremental.NullWriterFactoryTest
Tests run: 1, Failures: 0, Errors: 0, Skipped: 0, Time elapsed: 0.004 sec - in org.pitest.mutationtest.incremental.NullWriterFactoryTest
Running org.pitest.mutationtest.incremental.XStreamHistoryStoreTest
Tests run: 4, Failures: 0, Errors: 0, Skipped: 0, Time elapsed: 0.089 sec - in org.pitest.mutationtest.incremental.XStreamHistoryStoreTest
Running org.pitest.mutationtest.incremental.DefaultCodeHistoryTest
Tests run: 6, Failures: 0, Errors: 0, Skipped: 0, Time elapsed: 0.017 sec - in org.pitest.mutationtest.incremental.DefaultCodeHistoryTest
Running org.pitest.mutationtest.incremental.NullHistoryStoreTest
Tests run: 2, Failures: 0, Errors: 0, Skipped: 0, Time elapsed: 0 sec - in org.pitest.mutationtest.incremental.NullHistoryStoreTest
Running org.pitest.mutationtest.incremental.IncrementalAnalyserTest
Tests run: 7, Failures: 0, Errors: 0, Skipped: 0, Time elapsed: 0.028 sec - in org.pitest.mutationtest.incremental.IncrementalAnalyserTest
Running org.pitest.mutationtest.incremental.HistoryListenerTest
Tests run: 1, Failures: 0, Errors: 0, Skipped: 0, Time elapsed: 0.002 sec - in org.pitest.mutationtest.incremental.HistoryListenerTest
Running org.pitest.mutationtest.report.xml.XMLReportListenerTest
Tests run: 4, Failures: 0, Errors: 0, Skipped: 0, Time elapsed: 0 sec - in org.pitest.mutationtest.report.xml.XMLReportListenerTest
Running org.pitest.mutationtest.report.csv.CSVReportListenerTest
Tests run: 2, Failures: 0, Errors: 0, Skipped: 0, Time elapsed: 0.008 sec - in org.pitest.mutationtest.report.csv.CSVReportListenerTest
Running org.pitest.mutationtest.tooling.JarCreatingJarFinderTest
Tests run: 9, Failures: 0, Errors: 0, Skipped: 0, Time elapsed: 1.086 sec - in org.pitest.mutationtest.tooling.JarCreatingJarFinderTest
Running org.pitest.mutationtest.tooling.SpinnerListenerTest
Tests run: 1, Failures: 0, Errors: 0, Skipped: 0, Time elapsed: 0.001 sec - in org.pitest.mutationtest.tooling.SpinnerListenerTest
Running org.pitest.mutationtest.tooling.MutationCoverageReportTest
================================================================================
- Timings
================================================================================
> build mutation tests : < 1 second
> run mutation analysis : < 1 second
--------------------------------------------------------------------------------
> Total  : < 1 second
--------------------------------------------------------------------------------
================================================================================
- Statistics
================================================================================
>> Generated 0 mutations Killed 0 (100%)
>> Ran 0 tests (0 tests per mutation)
================================================================================
- Mutators
================================================================================
================================================================================
- Timings
================================================================================
> build mutation tests : < 1 second
> run mutation analysis : < 1 second
--------------------------------------------------------------------------------
> Total  : < 1 second
--------------------------------------------------------------------------------
================================================================================
- Statistics
================================================================================
>> Generated 0 mutations Killed 0 (100%)
>> Ran 0 tests (0 tests per mutation)
================================================================================
- Mutators
================================================================================
================================================================================
- Timings
================================================================================
> build mutation tests : < 1 second
> run mutation analysis : < 1 second
--------------------------------------------------------------------------------
> Total  : < 1 second
--------------------------------------------------------------------------------
================================================================================
- Statistics
================================================================================
>> Generated 0 mutations Killed 0 (100%)
>> Ran 0 tests (0 tests per mutation)
================================================================================
- Mutators
================================================================================
================================================================================
- Timings
================================================================================
> build mutation tests : < 1 second
> run mutation analysis : < 1 second
--------------------------------------------------------------------------------
> Total  : < 1 second
--------------------------------------------------------------------------------
================================================================================
- Statistics
================================================================================
>> Generated 0 mutations Killed 0 (100%)
>> Ran 0 tests (0 tests per mutation)
================================================================================
- Mutators
================================================================================
Tests run: 6, Failures: 0, Errors: 0, Skipped: 1, Time elapsed: 0.103 sec - in org.pitest.mutationtest.tooling.MutationCoverageReportTest
Running org.pitest.mutationtest.tooling.DirectorySourceLocatorTest
Tests run: 2, Failures: 0, Errors: 0, Skipped: 0, Time elapsed: 0.007 sec - in org.pitest.mutationtest.tooling.DirectorySourceLocatorTest
Running org.pitest.mutationtest.filter.LimitNumberOfMutationPerClassFilterTest
Tests run: 4, Failures: 0, Errors: 0, Skipped: 0, Time elapsed: 0.021 sec - in org.pitest.mutationtest.filter.LimitNumberOfMutationPerClassFilterTest
Running org.pitest.mutationtest.filter.LimitNumberOfMutationsPerClassFilterFactoryTest
Tests run: 3, Failures: 0, Errors: 0, Skipped: 0, Time elapsed: 0 sec - in org.pitest.mutationtest.filter.LimitNumberOfMutationsPerClassFilterFactoryTest
Running org.pitest.mutationtest.filter.KotlinFilterTest
Tests run: 4, Failures: 0, Errors: 0, Skipped: 0, Time elapsed: 0.007 sec - in org.pitest.mutationtest.filter.KotlinFilterTest
Running org.pitest.mutationtest.verify.DefaultBuildVerifierTest
Tests run: 6, Failures: 0, Errors: 0, Skipped: 0, Time elapsed: 0.014 sec - in org.pitest.mutationtest.verify.DefaultBuildVerifierTest
Running org.pitest.mutationtest.MutationResultTest
Tests run: 4, Failures: 0, Errors: 0, Skipped: 0, Time elapsed: 0.334 sec - in org.pitest.mutationtest.MutationResultTest
Running org.pitest.mutationtest.MutationStatusMapTest
Tests run: 8, Failures: 0, Errors: 0, Skipped: 0, Time elapsed: 0.008 sec - in org.pitest.mutationtest.MutationStatusMapTest
Running org.pitest.mutationtest.MutationMetaDataTest
Tests run: 3, Failures: 0, Errors: 0, Skipped: 0, Time elapsed: 0.04 sec - in org.pitest.mutationtest.MutationMetaDataTest
Running org.pitest.coverage.export.DefaultCoverageExporterTest
Tests run: 2, Failures: 0, Errors: 0, Skipped: 0, Time elapsed: 0.002 sec - in org.pitest.coverage.export.DefaultCoverageExporterTest
Running org.pitest.coverage.execute.ReceiveTest
Tests run: 3, Failures: 0, Errors: 0, Skipped: 0, Time elapsed: 0.028 sec - in org.pitest.coverage.execute.ReceiveTest
Running org.pitest.coverage.execute.SendDataTest
Tests run: 2, Failures: 0, Errors: 0, Skipped: 0, Time elapsed: 0.001 sec - in org.pitest.coverage.execute.SendDataTest
Running org.pitest.coverage.CoverageSummaryTest
Tests run: 4, Failures: 0, Errors: 0, Skipped: 0, Time elapsed: 0.011 sec - in org.pitest.coverage.CoverageSummaryTest
Running org.pitest.coverage.CoverageDataTest
Tests run: 16, Failures: 0, Errors: 0, Skipped: 0, Time elapsed: 0.039 sec - in org.pitest.coverage.CoverageDataTest
Running org.pitest.classinfo.NameToClassInfoTest
Tests run: 1, Failures: 0, Errors: 0, Skipped: 0, Time elapsed: 0.004 sec - in org.pitest.classinfo.NameToClassInfoTest
Running org.pitest.classinfo.ClassInfoTest
Tests run: 7, Failures: 0, Errors: 0, Skipped: 0, Time elapsed: 0.009 sec - in org.pitest.classinfo.ClassInfoTest
Running org.pitest.classinfo.RepositoryTest
Tests run: 26, Failures: 0, Errors: 0, Skipped: 0, Time elapsed: 0.085 sec - in org.pitest.classinfo.RepositoryTest
Running org.pitest.classinfo.TestToClassMapperTest
Tests run: 3, Failures: 0, Errors: 0, Skipped: 0, Time elapsed: 0.003 sec - in org.pitest.classinfo.TestToClassMapperTest
Running org.pitest.classinfo.AddlerHashTest
Tests run: 3, Failures: 0, Errors: 0, Skipped: 0, Time elapsed: 0.008 sec - in org.pitest.classinfo.AddlerHashTest
Running org.pitest.bytecode.analysis.InstructionMatchersTest
Tests run: 3, Failures: 0, Errors: 0, Skipped: 0, Time elapsed: 0.004 sec - in org.pitest.bytecode.analysis.InstructionMatchersTest
Running org.pitest.bytecode.analysis.ClassTreeTest
Tests run: 2, Failures: 0, Errors: 0, Skipped: 0, Time elapsed: 0.004 sec - in org.pitest.bytecode.analysis.ClassTreeTest
Running org.pitest.util.SocketReadingCallableTest
Tests run: 4, Failures: 0, Errors: 0, Skipped: 0, Time elapsed: 0.054 sec - in org.pitest.util.SocketReadingCallableTest
Running org.pitest.util.ServiceLoaderTest
Tests run: 2, Failures: 0, Errors: 0, Skipped: 0, Time elapsed: 0.001 sec - in org.pitest.util.ServiceLoaderTest
Running org.pitest.util.TimeSpanTest
Tests run: 4, Failures: 0, Errors: 0, Skipped: 0, Time elapsed: 0 sec - in org.pitest.util.TimeSpanTest
Running org.pitest.util.SocketFinderTest
Tests run: 1, Failures: 0, Errors: 0, Skipped: 0, Time elapsed: 0.005 sec - in org.pitest.util.SocketFinderTest

Results :

Failed tests: 
  SimpleInfiniteLoopInterceptorTest.shouldMatchRealInfiniteLoopFromJodaTimeMutants:172->checkFiltered:214 [With javac compiler did not match as expected Byte code is 
   L0
    LINENUMBER 183 L0
    ALOAD 1
    INVOKEINTERFACE org/joda/time/ReadablePartial.size ()I
    ISTORE 3
   L1
    LINENUMBER 184 L1
    ICONST_0
    ISTORE 4
   L2
    GOTO L3
   L4
    LINENUMBER 185 L4
    ALOAD 2
    ILOAD 4
    IALOAD
    ISTORE 5
   L5
    LINENUMBER 186 L5
    ALOAD 1
    ILOAD 4
    INVOKEINTERFACE org/joda/time/ReadablePartial.getField (I)Lorg/joda/time/DateTimeField;
    ASTORE 6
   L6
    LINENUMBER 187 L6
    ILOAD 5
    ALOAD 6
    INVOKEVIRTUAL org/joda/time/DateTimeField.getMinimumValue ()I
    IF_ICMPGE L7
   L8
    LINENUMBER 188 L8
    NEW org/joda/time/IllegalFieldValueException
    DUP
   L9
    LINENUMBER 189 L9
    ALOAD 6
    INVOKEVIRTUAL org/joda/time/DateTimeField.getType ()Lorg/joda/time/DateTimeFieldType;
    ILOAD 5
    INVOKESTATIC java/lang/Integer.valueOf (I)Ljava/lang/Integer;
   L10
    LINENUMBER 190 L10
    ALOAD 6
    INVOKEVIRTUAL org/joda/time/DateTimeField.getMinimumValue ()I
    INVOKESTATIC java/lang/Integer.valueOf (I)Ljava/lang/Integer;
    ACONST_NULL
   L11
    LINENUMBER 188 L11
    INVOKESPECIAL org/joda/time/IllegalFieldValueException.<init> (Lorg/joda/time/DateTimeFieldType;Ljava/lang/Number;Ljava/lang/Number;Ljava/lang/Number;)V
    ATHROW
   L7
    LINENUMBER 192 L7
    ILOAD 5
    ALOAD 6
    INVOKEVIRTUAL org/joda/time/DateTimeField.getMaximumValue ()I
    IF_ICMPLE L12
   L13
    LINENUMBER 193 L13
    NEW org/joda/time/IllegalFieldValueException
    DUP
   L14
    LINENUMBER 194 L14
    ALOAD 6
    INVOKEVIRTUAL org/joda/time/DateTimeField.getType ()Lorg/joda/time/DateTimeFieldType;
    ILOAD 5
    INVOKESTATIC java/lang/Integer.valueOf (I)Ljava/lang/Integer;
   L15
    LINENUMBER 195 L15
    ACONST_NULL
    ALOAD 6
    INVOKEVIRTUAL org/joda/time/DateTimeField.getMaximumValue ()I
    INVOKESTATIC java/lang/Integer.valueOf (I)Ljava/lang/Integer;
   L16
    LINENUMBER 193 L16
    INVOKESPECIAL org/joda/time/IllegalFieldValueException.<init> (Lorg/joda/time/DateTimeFieldType;Ljava/lang/Number;Ljava/lang/Number;Ljava/lang/Number;)V
    ATHROW
   L12
    LINENUMBER 184 L12
    NOP
   L3
    ILOAD 4
    ILOAD 3
    IF_ICMPLT L4
   L17
    LINENUMBER 199 L17
    ICONST_0
    ISTORE 4
   L18
    GOTO L19
   L20
    LINENUMBER 200 L20
    ALOAD 2
    ILOAD 4
    IALOAD
    ISTORE 5
   L21
    LINENUMBER 201 L21
    ALOAD 1
    ILOAD 4
    INVOKEINTERFACE org/joda/time/ReadablePartial.getField (I)Lorg/joda/time/DateTimeField;
    ASTORE 6
   L22
    LINENUMBER 202 L22
    ILOAD 5
    ALOAD 6
    ALOAD 1
    ALOAD 2
    INVOKEVIRTUAL org/joda/time/DateTimeField.getMinimumValue (Lorg/joda/time/ReadablePartial;[I)I
    IF_ICMPGE L23
   L24
    LINENUMBER 203 L24
    NEW org/joda/time/IllegalFieldValueException
    DUP
   L25
    LINENUMBER 204 L25
    ALOAD 6
    INVOKEVIRTUAL org/joda/time/DateTimeField.getType ()Lorg/joda/time/DateTimeFieldType;
    ILOAD 5
    INVOKESTATIC java/lang/Integer.valueOf (I)Ljava/lang/Integer;
   L26
    LINENUMBER 205 L26
    ALOAD 6
    ALOAD 1
    ALOAD 2
    INVOKEVIRTUAL org/joda/time/DateTimeField.getMinimumValue (Lorg/joda/time/ReadablePartial;[I)I
    INVOKESTATIC java/lang/Integer.valueOf (I)Ljava/lang/Integer;
    ACONST_NULL
   L27
    LINENUMBER 203 L27
    INVOKESPECIAL org/joda/time/IllegalFieldValueException.<init> (Lorg/joda/time/DateTimeFieldType;Ljava/lang/Number;Ljava/lang/Number;Ljava/lang/Number;)V
    ATHROW
   L23
    LINENUMBER 207 L23
    ILOAD 5
    ALOAD 6
    ALOAD 1
    ALOAD 2
    INVOKEVIRTUAL org/joda/time/DateTimeField.getMaximumValue (Lorg/joda/time/ReadablePartial;[I)I
    IF_ICMPLE L28
   L29
    LINENUMBER 208 L29
    NEW org/joda/time/IllegalFieldValueException
    DUP
   L30
    LINENUMBER 209 L30
    ALOAD 6
    INVOKEVIRTUAL org/joda/time/DateTimeField.getType ()Lorg/joda/time/DateTimeFieldType;
    ILOAD 5
    INVOKESTATIC java/lang/Integer.valueOf (I)Ljava/lang/Integer;
   L31
    LINENUMBER 210 L31
    ACONST_NULL
    ALOAD 6
    ALOAD 1
    ALOAD 2
    INVOKEVIRTUAL org/joda/time/DateTimeField.getMaximumValue (Lorg/joda/time/ReadablePartial;[I)I
    INVOKESTATIC java/lang/Integer.valueOf (I)Ljava/lang/Integer;
   L32
    LINENUMBER 208 L32
    INVOKESPECIAL org/joda/time/IllegalFieldValueException.<init> (Lorg/joda/time/DateTimeFieldType;Ljava/lang/Number;Ljava/lang/Number;Ljava/lang/Number;)V
    ATHROW
   L28
    LINENUMBER 199 L28
    IINC 4 1
   L19
    ILOAD 4
    ILOAD 3
    IF_ICMPLT L20
   L33
    LINENUMBER 213 L33
    RETURN
   L34
    LOCALVARIABLE this Lorg/joda/time/chrono/BaseChronology; L0 L34 0
    LOCALVARIABLE partial Lorg/joda/time/ReadablePartial; L0 L34 1
    LOCALVARIABLE values [I L0 L34 2
    LOCALVARIABLE size I L1 L34 3
    LOCALVARIABLE i I L2 L17 4
    LOCALVARIABLE value I L5 L12 5
    LOCALVARIABLE field Lorg/joda/time/DateTimeField; L6 L12 6
    LOCALVARIABLE i I L18 L33 4
    LOCALVARIABLE value I L21 L28 5
    LOCALVARIABLE field Lorg/joda/time/DateTimeField; L22 L28 6
    MAXSTACK = 8
    MAXLOCALS = 7
] expected:<[tru]e> but was:<[fals]e>

Tests run: 305, Failures: 1, Errors: 0, Skipped: 5

[INFO] ------------------------------------------------------------------------
[INFO] Reactor Summary:
[INFO] 
[INFO] pitest-parent ...................................... SUCCESS [  0.013 s]
[INFO] Build Config ....................................... SUCCESS [  2.577 s]
[INFO] pitest ............................................. SUCCESS [ 19.777 s]
[INFO] pitest-entry ....................................... FAILURE [  6.766 s]
[INFO] pitest-html-report ................................. SKIPPED
[INFO] pitest-maven ....................................... SKIPPED
[INFO] pitest-command-line ................................ SKIPPED
[INFO] pitest-ant ......................................... SKIPPED
[INFO] pitest-maven-verification .......................... SKIPPED
[INFO] pitest-java8-verification .......................... SKIPPED
[INFO] pitest-groovy-verification ......................... SKIPPED
[INFO] ------------------------------------------------------------------------
[INFO] BUILD FAILURE
[INFO] ------------------------------------------------------------------------
[INFO] Total time: 29.496 s
[INFO] Finished at: 2020-02-16T11:39:20+01:00
[INFO] Final Memory: 18M/67M
[INFO] ------------------------------------------------------------------------
[ERROR] Failed to execute goal org.apache.maven.plugins:maven-surefire-plugin:2.17:test (default-test) on project pitest-entry: There are test failures.
[ERROR] 
[ERROR] Please refer to /scratch/dginelli/workspace/repairnator-repairnator-experiments-hcoles-pitest-247833128-20170628-100234_bugonly-firstCommit/pitest-entry/target/surefire-reports for the individual test results.
[ERROR] -> [Help 1]
org.apache.maven.lifecycle.LifecycleExecutionException: Failed to execute goal org.apache.maven.plugins:maven-surefire-plugin:2.17:test (default-test) on project pitest-entry: There are test failures.

Please refer to /scratch/dginelli/workspace/repairnator-repairnator-experiments-hcoles-pitest-247833128-20170628-100234_bugonly-firstCommit/pitest-entry/target/surefire-reports for the individual test results.
	at org.apache.maven.lifecycle.internal.MojoExecutor.execute(MojoExecutor.java:212)
	at org.apache.maven.lifecycle.internal.MojoExecutor.execute(MojoExecutor.java:153)
	at org.apache.maven.lifecycle.internal.MojoExecutor.execute(MojoExecutor.java:145)
	at org.apache.maven.lifecycle.internal.LifecycleModuleBuilder.buildProject(LifecycleModuleBuilder.java:116)
	at org.apache.maven.lifecycle.internal.LifecycleModuleBuilder.buildProject(LifecycleModuleBuilder.java:80)
	at org.apache.maven.lifecycle.internal.builder.singlethreaded.SingleThreadedBuilder.build(SingleThreadedBuilder.java:51)
	at org.apache.maven.lifecycle.internal.LifecycleStarter.execute(LifecycleStarter.java:128)
	at org.apache.maven.DefaultMaven.doExecute(DefaultMaven.java:307)
	at org.apache.maven.DefaultMaven.doExecute(DefaultMaven.java:193)
	at org.apache.maven.DefaultMaven.execute(DefaultMaven.java:106)
	at org.apache.maven.cli.MavenCli.execute(MavenCli.java:863)
	at org.apache.maven.cli.MavenCli.doMain(MavenCli.java:288)
	at org.apache.maven.cli.MavenCli.main(MavenCli.java:199)
	at sun.reflect.NativeMethodAccessorImpl.invoke0(Native Method)
	at sun.reflect.NativeMethodAccessorImpl.invoke(NativeMethodAccessorImpl.java:62)
	at sun.reflect.DelegatingMethodAccessorImpl.invoke(DelegatingMethodAccessorImpl.java:43)
	at java.lang.reflect.Method.invoke(Method.java:498)
	at org.codehaus.plexus.classworlds.launcher.Launcher.launchEnhanced(Launcher.java:289)
	at org.codehaus.plexus.classworlds.launcher.Launcher.launch(Launcher.java:229)
	at org.codehaus.plexus.classworlds.launcher.Launcher.mainWithExitCode(Launcher.java:415)
	at org.codehaus.plexus.classworlds.launcher.Launcher.main(Launcher.java:356)
Caused by: org.apache.maven.plugin.MojoFailureException: There are test failures.

Please refer to /scratch/dginelli/workspace/repairnator-repairnator-experiments-hcoles-pitest-247833128-20170628-100234_bugonly-firstCommit/pitest-entry/target/surefire-reports for the individual test results.
	at org.apache.maven.plugin.surefire.SurefireHelper.reportExecution(SurefireHelper.java:82)
	at org.apache.maven.plugin.surefire.SurefirePlugin.handleSummary(SurefirePlugin.java:195)
	at org.apache.maven.plugin.surefire.AbstractSurefireMojo.executeAfterPreconditionsChecked(AbstractSurefireMojo.java:861)
	at org.apache.maven.plugin.surefire.AbstractSurefireMojo.execute(AbstractSurefireMojo.java:729)
	at org.apache.maven.plugin.DefaultBuildPluginManager.executeMojo(DefaultBuildPluginManager.java:134)
	at org.apache.maven.lifecycle.internal.MojoExecutor.execute(MojoExecutor.java:207)
	... 20 more
[ERROR] 
[ERROR] Re-run Maven using the -X switch to enable full debug logging.
[ERROR] 
[ERROR] For more information about the errors and possible solutions, please read the following articles:
[ERROR] [Help 1] http://cwiki.apache.org/confluence/display/MAVEN/MojoFailureException
[ERROR] 
[ERROR] After correcting the problems, you can resume the build with the command
[ERROR]   mvn <goals> -rf :pitest-entry
